demakein/__init__.py
demakein/__main__.py
demakein/all.py
demakein/config.py
demakein/cpp.py
demakein/design.py
demakein/design_flute.py
demakein/design_shawm.py
demakein/design_whistle.py
demakein/engine_cgal.py
demakein/engine_trimesh.py
demakein/geom.py
demakein/grace.py
demakein/legion.py
demakein/make.py
demakein/make_bauble.py
demakein/make_cork.py
demakein/make_flute.py
demakein/make_mouthpiece.py
demakein/make_panpipe.py
demakein/make_reed.py
demakein/make_shawm.py
demakein/make_whistle.py
demakein/make_windcap.py
demakein/mask.py
demakein/optimize.py
demakein/pack.py
demakein/profile.py
demakein/selection.py
demakein/shape.py
demakein/sketch.py
demakein/svg.py
demakein/tune.py
demakein/workspace.py
demakein/raphs_curves/__init__.py
demakein/raphs_curves/band.py
demakein/raphs_curves/bezfigs.py
demakein/raphs_curves/bigmat.py
demakein/raphs_curves/cloth_off.py
demakein/raphs_curves/clothoid.py
demakein/raphs_curves/cornu.py
demakein/raphs_curves/euler-elastica.py
demakein/raphs_curves/fromcubic.py
demakein/raphs_curves/mecsolve.py
demakein/raphs_curves/mvc.py
demakein/raphs_curves/numintsynth.py
demakein/raphs_curves/offset.py
demakein/raphs_curves/pcorn.py
demakein/raphs_curves/plot_solve_clothoid.py
demakein/raphs_curves/poly3.py
demakein/raphs_curves/polymat-bad.py
demakein/raphs_curves/polymat.py
demakein/raphs_curves/tocubic.py
demakein-1.1.dist-info/METADATA
demakein-1.1.dist-info/WHEEL
demakein-1.1.dist-info/entry_points.txt
demakein-1.1.dist-info/licenses/LICENSE
demakein-1.1.dist-info/RECORD
