Metadata-Version: 2.4
Name: demakein
Version: 1.1
Summary: Design woodwind instruments and make them with a 3D printer or CNC mill.
Project-URL: Homepage, https://logarithmic.net/pfh/design
Project-URL: Source, https://github.com/pfh/demakein
Author-email: Paul Harrison <paul.francis.harrison@gmail.com>
License-Expression: LGPL-2.1
License-File: LICENSE
Classifier: Operating System :: OS Independent
Classifier: Programming Language :: Python :: 3
Classifier: Topic :: Multimedia :: Graphics :: 3D Modeling
Classifier: Topic :: Scientific/Engineering
Requires-Python: >=3.8
Requires-Dist: manifold3d
Requires-Dist: scipy
Requires-Dist: shapely
Requires-Dist: trimesh
